{"time": ["None", 97.752, "None", 97.22, 148.706, 96.397, 138.418, "None", "None", 93.984, "None", 128.344, 106.714, 100.803, 100.425, 100.485, 100.037, 119.729, 107.88, 99.25, 98.685, "None", "None"], "lap": [1.0, 2.0, 3.0, 4.0, 5.0, 6.0, 7.0, 8.0, 9.0, 10.0, 11.0, 12.0, 13.0, 14.0, 15.0, 16.0, 17.0, 18.0, 19.0, 20.0, 21.0, 22.0, 23.0], "compound": ["HARD", "HARD", "HARD", "HARD", "HARD", "HARD", "HARD", "HARD", "SOFT", "SOFT", "SOFT", "HARD", "HARD", "HARD", "HARD", "HARD", "HARD", "HARD", "SOFT", "SOFT", "SOFT", "SOFT", "SOFT"], "stint": [1, 1, 1, 1, 1, 1, 1, 2, 3, 3, 3, 4, 4, 4, 4, 4, 4, 4, 5, 5, 5, 5, 5], "s1": [51.736, 25.131, 35.941, 24.651, 35.393, 24.344, 29.251, 33.708, 43.677, 23.63, 40.815, 44.127, 25.589, 25.489, 25.281, 25.337, 25.212, 25.18, 33.25, 25.03, 24.947, 25.018, 29.229], "s2": [38.76, 29.677, 46.051, 29.494, 53.509, 29.428, 34.148, 29.552, 45.912, 28.682, 45.528, 30.718, 30.488, 30.9, 30.756, 31.152, 30.595, 30.574, 30.357, 30.392, 30.167, 32.827, 33.212], "s3": [68.994, 42.944, 79.942, 43.075, 59.804, 42.625, 75.019, "None", 62.697, 41.672, "None", 53.499, 50.637, 44.414, 44.388, 43.996, 44.23, 63.975, 44.273, 43.828, 43.571, 95.799, "None"], "life": [1, 2, 3, 4, 5, 6, 7, 8, 1, 2, 3, 9, 10, 11, 12, 13, 14, 15, 4, 5, 6, 7, 8], "pos": ["None", "None", "None", "None", "None", "None", "None", "None", "None", "None", "None", "None", "None", "None", "None", "None", "None", "None", "None", "None", "None", "None", "None"], "status": ["1", "1", "1", "1", "1", "1", "1", "1", "1", "1", "1", "1", "1", "1", "1", "1", "1", "1", "1", "1", "1", "1", "1"], "pb": [false, true, false, true, false, true, false, false, false, true, false, false, false, false, false, false, false, false, false, false, false, false, false]}