{"time": ["None", 97.887, "None", 149.956, 96.908, 114.859, "None", 96.656, 127.664, "None", 96.97, 119.549, "None", 96.196, 124.87], "lap": [1.0, 2.0, 3.0, 4.0, 5.0, 6.0, 7.0, 8.0, 9.0, 10.0, 11.0, 12.0, 13.0, 14.0, 15.0], "compound": ["SOFT", "SOFT", "SOFT", "SOFT", "SOFT", "SOFT", "SOFT", "SOFT", "SOFT", "SOFT", "SOFT", "SOFT", "SOFT", "SOFT", "SOFT"], "stint": [1, 1, 1, 1, 1, 1, 2, 2, 2, 3, 3, 3, 4, 4, 4], "s1": ["None", 26.392, 40.014, 40.69, 26.103, 29.542, "None", 26.073, 35.098, "None", 26.273, 34.867, "None", 26.143, 34.1], "s2": [48.692, 39.516, 62.67, 65.244, 39.04, 44.064, 44.996, 39.055, 49.537, 49.652, 38.955, 47.149, 44.786, 38.556, 48.745], "s3": [40.175, 31.979, 51.107, 44.022, 31.765, 41.253, 44.27, 31.528, 43.029, 39.52, 31.742, 37.533, 50.983, 31.497, 42.025], "life": [1, 2, 3, 4, 5, 6, 1, 2, 3, 4, 5, 6, 1, 2, 3], "pos": ["None", "None", "None", "None", "None", "None", "None", "None", "None", "None", "None", "None", "None", "None", "None"], "status": ["1", "1", "1", "1", "1", "1", "1", "1", "1", "1", "1", "1", "1", "1", "1"], "pb": [false, true, false, false, true, false, false, true, false, false, true, false, false, false, false]}