{"time": ["None", 103.897, 140.385, 102.957, 141.165, 146.743, "None", "None", 102.088, 141.719, 138.493, 102.573, 130.66, "None", 101.814, 128.658, "None", 105.97, "None"], "lap": [1.0, 2.0, 3.0, 4.0, 5.0, 6.0, 7.0, 8.0, 9.0, 10.0, 11.0, 12.0, 13.0, 14.0, 15.0, 16.0, 17.0, 18.0, 19.0], "compound": ["SOFT", "SOFT", "SOFT", "SOFT", "SOFT", "SOFT", "SOFT", "SOFT", "SOFT", "SOFT", "SOFT", "SOFT", "SOFT", "SOFT", "SOFT", "SOFT", "SOFT", "SOFT", "SOFT"], "stint": [1, 1, 1, 1, 1, 2, 2, 3, 3, 3, 3, 3, 3, 4, 4, 4, 5, 5, 5], "s1": ["None", 36.71, 55.267, 36.293, 47.942, 67.696, 36.265, "None", 35.88, 49.592, 57.833, 36.13, 46.141, "None", 35.729, 45.2, "None", 36.18, 52.777], "s2": [51.971, 42.121, 57.752, 41.602, 54.571, 52.578, 41.513, 50.971, 41.182, 59.906, 53.961, 41.345, 49.931, 51.988, 41.057, 51.084, 53.771, 42.372, 53.76], "s3": [26.717, 25.066, 27.366, 25.062, 38.652, 26.469, "None", 26.493, 25.026, 32.221, 26.699, 25.098, 34.588, 26.51, 25.028, 32.374, 26.747, 27.418, "None"], "life": [1, 2, 3, 4, 5, 6, 7, 1, 2, 3, 4, 5, 6, 1, 2, 3, 1, 2, 3], "pos": ["None", "None", "None", "None", "None", "None", "None", "None", "None", "None", "None", "None", "None", "None", "None", "None", "None", "None", "None"], "status": ["1", "12", "12", "1", "1", "12", "125", "1", "1", "1", "12", "12", "1", "12", "1", "1", "1", "1", "1"], "pb": [false, true, false, true, false, false, false, false, true, false, false, false, false, false, true, false, false, false, false]}