{"time": [115.919, 102.691, 99.906, "None", 103.402, 118.371, 106.071, 95.305, 97.796, 106.201, 95.49, 99.469, 94.11, "None"], "lap": [1.0, 2.0, 3.0, 4.0, 5.0, 6.0, 7.0, 8.0, 9.0, 10.0, 11.0, 12.0, 13.0, 14.0], "compound": ["WET", "WET", "WET", "WET", "WET", "WET", "INTERMEDIATE", "INTERMEDIATE", "INTERMEDIATE", "INTERMEDIATE", "INTERMEDIATE", "INTERMEDIATE", "INTERMEDIATE", "INTERMEDIATE"], "stint": [1, 1, 1, 1, 2, 2, 3, 3, 3, 3, 3, 3, 3, 3], "s1": [34.555, 30.445, 29.003, 29.717, 31.833, 27.947, 34.948, 27.507, 27.156, 34.235, 27.337, 31.041, 26.985, 31.503], "s2": [35.459, 32.947, 32.103, 36.346, 32.995, 31.371, 32.746, 30.495, 31.098, 33.027, 30.924, 31.273, 30.432, 33.864], "s3": [45.905, 39.299, 38.8, "None", 38.574, 59.053, 38.377, 37.303, 39.542, 38.939, 37.229, 37.155, 36.693, "None"], "life": [1, 2, 3, 4, 5, 6, 1, 2, 3, 4, 5, 6, 7, 8], "pos": ["None", "None", "None", "None", "None", "None", "None", "None", "None", "None", "None", "None", "None", "None"], "status": ["1", "1", "12", "12", "1", "1", "1", "1", "12", "21", "12", "21", "1", "1"], "pb": [false, true, true, false, false, false, false, true, false, false, false, false, true, false]}