{"time": [111.362, 103.014, 104.746, 99.148, "None", 101.886, 96.719, 95.643, "None", 119.538, 102.849, "None", 100.656, 99.134, 96.335, 129.853, "None"], "lap": [1.0, 2.0, 3.0, 4.0, 5.0, 6.0, 7.0, 8.0, 9.0, 10.0, 11.0, 12.0, 13.0, 14.0, 15.0, 16.0, 17.0], "compound": ["WET", "WET", "WET", "WET", "WET", "WET", "WET", "WET", "WET", "INTERMEDIATE", "INTERMEDIATE", "INTERMEDIATE", "INTERMEDIATE", "INTERMEDIATE", "INTERMEDIATE", "INTERMEDIATE", "INTERMEDIATE"], "stint": [1, 1, 1, 1, 1, 2, 2, 2, 2, 3, 3, 3, 3, 3, 3, 3, 3], "s1": [34.958, 30.571, 32.018, 29.077, 28.313, 31.281, 27.477, 27.414, 27.376, 37.357, 28.09, 85.627, 28.46, 29.908, 28.233, 27.796, 35.943], "s2": [35.612, 33.361, 33.729, 32.027, 32.923, 32.673, 31.781, 30.872, 30.867, 34.43, 33.24, 33.018, 31.702, 31.699, 31.182, 30.897, 36.889], "s3": [40.792, 39.082, 38.999, 38.044, "None", 37.932, 37.461, 37.357, "None", 47.751, 41.519, 40.145, 40.494, 37.527, 36.92, 71.16, "None"], "life": [1, 2, 3, 4, 5, 6, 7, 8, 9, 1, 2, 3, 4, 5, 6, 7, 8], "pos": ["None", "None", "None", "None", "None", "None", "None", "None", "None", "None", "None", "None", "None", "None", "None", "None", "None"], "status": ["1", "1", "12", "1", "12", "1", "1", "1", "1", "1", "1", "12", "12", "21", "1", "1", "1"], "pb": [false, true, false, true, false, false, true, true, false, false, false, false, false, false, false, false, false]}