{"time": ["None", 93.999, 134.282, 94.067, 134.686, 134.048, 94.167, 123.041, "None", "None", 93.974, 123.701, 119.226, 93.872, 135.283, 146.932, "None", 116.641, "None", "None"], "lap": [1.0, 2.0, 3.0, 4.0, 5.0, 6.0, 7.0, 8.0, 9.0, 10.0, 11.0, 12.0, 13.0, 14.0, 15.0, 16.0, 17.0, 18.0, 19.0, 20.0], "compound": ["SOFT", "SOFT", "SOFT", "SOFT", "SOFT", "SOFT", "SOFT", "SOFT", "SOFT", "SOFT", "SOFT", "SOFT", "SOFT", "SOFT", "SOFT", "SOFT", "SOFT", "SOFT", "SOFT", "SOFT"], "stint": [1, 1, 1, 1, 1, 1, 1, 1, 2, 3, 3, 3, 3, 3, 3, 4, 4, 5, 5, 5], "s1": [45.147, 23.646, 34.205, 23.613, 30.832, 35.432, 23.65, 27.433, 59.269, 48.059, 23.684, 32.842, 31.805, 23.483, 29.721, 57.587, 23.646, 40.078, 26.64, 29.879], "s2": [46.029, 28.729, 44.512, 28.756, 41.446, 43.392, 28.805, 32.074, 34.932, 53.991, 28.689, 38.252, 37.553, 28.818, 35.74, 35.905, 32.894, 30.951, 30.604, 33.543], "s3": [64.799, 41.624, 55.565, 41.698, 62.408, 55.224, 41.712, 63.534, "None", 62.851, 41.601, 52.607, 49.868, 41.571, 69.822, 53.44, "None", 45.612, "None", "None"], "life": [1, 2, 3, 4, 5, 6, 7, 8, 9, 1, 2, 3, 4, 5, 6, 7, 8, 9, 10, 11], "pos": ["None", "None", "None", "None", "None", "None", "None", "None", "None", "None", "None", "None", "None", "None", "None", "None", "None", "None", "None", "None"], "status": ["1", "1", "1", "1", "1", "1", "1", "1", "1", "1", "1", "12", "1", "1", "1", "1", "12", "1", "1", "1"], "pb": [false, true, false, false, false, false, false, false, false, false, true, false, false, true, false, false, false, false, false, false]}