{"time": ["None", 84.113, 121.54, 105.661, 84.646, 126.468, 83.806, 109.608, "None", "None", "None", 83.283, 121.913, 135.682, 83.135, 96.128, "None", 86.817, 86.415, 86.374, 86.741, 86.859, 87.074, 100.652, 123.303], "lap": [1.0, 2.0, 3.0, 4.0, 5.0, 6.0, 7.0, 8.0, 9.0, 10.0, 11.0, 12.0, 13.0, 14.0, 15.0, 16.0, 17.0, 18.0, 19.0, 20.0, 21.0, 22.0, 23.0, 24.0, 25.0], "compound": ["MEDIUM", "MEDIUM", "MEDIUM", "MEDIUM", "MEDIUM", "MEDIUM", "MEDIUM", "MEDIUM", "SOFT", "SOFT", "SOFT", "SOFT", "SOFT", "SOFT", "SOFT", "SOFT", "SOFT", "SOFT", "SOFT", "SOFT", "SOFT", "SOFT", "SOFT", "SOFT", "SOFT"], "stint": [1, 1, 1, 1, 1, 1, 1, 1, 2, 2, 3, 3, 3, 4, 4, 4, 5, 5, 5, 5, 5, 5, 5, 5, 5], "s1": ["None", 27.576, 42.566, 36.231, 27.456, 42.432, 27.48, 33.333, "None", "None", "None", 27.403, 36.632, 65.436, 27.404, 31.068, "None", 28.25, 28.245, 28.11, 28.143, 28.216, 28.264, 29.763, 54.209], "s2": [33.3, 28.464, 41.721, 38.397, 28.977, 46.832, 28.25, 36.503, 32.809, "None", 33.585, 28.163, 41.545, 35.339, 28.097, 31.081, 30.5, 29.724, 29.535, 29.586, 29.543, 29.666, 29.8, 34.207, 32.587], "s3": [31.992, 28.073, 37.253, 31.033, 28.213, 37.204, 28.076, 39.772, 38.295, "None", 38.713, 27.717, 43.736, 34.907, 27.634, 33.979, 29.233, 28.843, 28.635, 28.678, 29.055, 28.977, 29.01, 36.682, 36.507], "life": [1, 2, 3, 4, 5, 6, 7, 8, 1, 2, 3, 4, 5, 6, 7, 8, 9, 10, 11, 12, 13, 14, 15, 16, 17], "pos": ["None", "None", "None", "None", "None", "None", "None", "None", "None", "None", "None", "None", "None", "None", "None", "None", "None", "None", "None", "None", "None", "None", "None", "None", "None"], "status": ["1", "1", "1", "1", "1", "1", "1", "1", "12", "251", "1", "1", "1", "1", "1", "1", "1", "1", "12", "1", "1", "12", "1", "1", "1"], "pb": [false, true, false, false, false, false, true, false, false, false, false, true, false, false, true, false, false, false, false, false, false, false, false, false, false]}