{"time": [112.735, 102.9, "None", 109.765, 98.124, 112.353, 104.58, 97.181, 103.22, 95.804, 99.425, 94.248, "None"], "lap": [1.0, 2.0, 3.0, 4.0, 5.0, 6.0, 7.0, 8.0, 9.0, 10.0, 11.0, 12.0, 13.0], "compound": ["WET", "WET", "WET", "WET", "WET", "WET", "INTERMEDIATE", "INTERMEDIATE", "INTERMEDIATE", "INTERMEDIATE", "INTERMEDIATE", "INTERMEDIATE", "INTERMEDIATE"], "stint": [1, 1, 1, 2, 2, 2, 3, 3, 3, 3, 3, 3, 3], "s1": [35.59, 30.255, 29.271, 34.867, 28.838, 27.696, 32.689, 28.025, 32.687, 27.668, 30.461, 27.432, 29.934], "s2": [35.715, 33.61, 32.869, 33.034, 31.791, 31.447, 33.441, 31.546, 32.524, 30.941, 31.113, 30.282, 32.129], "s3": [41.43, 39.035, "None", 41.864, 37.495, 53.21, 38.45, 37.61, 38.009, 37.195, 37.851, 36.534, "None"], "life": [1, 2, 3, 4, 5, 6, 1, 2, 3, 4, 5, 6, 7], "pos": ["None", "None", "None", "None", "None", "None", "None", "None", "None", "None", "None", "None", "None"], "status": ["1", "1", "12", "1", "1", "1", "1", "12", "21", "12", "21", "1", "1"], "pb": [false, true, false, false, true, false, false, true, false, true, false, true, false]}