{"time": ["None", 102.301, 99.299, 99.376, 98.128, 111.542, "None", 106.965, 95.502, 104.225, "None", "None"], "lap": [1.0, 2.0, 3.0, 4.0, 5.0, 6.0, 7.0, 8.0, 9.0, 10.0, 11.0, 12.0], "compound": ["WET", "WET", "WET", "WET", "WET", "WET", "INTERMEDIATE", "INTERMEDIATE", "INTERMEDIATE", "INTERMEDIATE", "INTERMEDIATE", "INTERMEDIATE"], "stint": [1, 1, 1, 1, 1, 1, 2, 2, 2, 2, 3, 3], "s1": ["None", 33.188, 31.827, 31.335, 30.994, 31.864, "None", 31.394, 30.416, 31.252, "None", 29.56], "s2": [41.436, 35.483, 34.414, 34.219, 34.186, 35.427, 38.757, 34.447, 32.767, 33.235, 34.517, "None"], "s3": [36.266, 33.63, 33.058, 33.822, 32.948, 44.251, 37.729, 41.124, 32.319, 39.738, 39.13, "None"], "life": [1, 2, 3, 4, 5, 6, 1, 2, 3, 4, 5, 6], "pos": ["None", "None", "None", "None", "None", "None", "None", "None", "None", "None", "None", "None"], "status": ["12", "12", "1", "1", "1", "1", "12", "1", "1", "1", "12", "125"], "pb": [false, true, true, false, true, false, false, false, true, false, false, false]}