{"time": ["None", 87.144, 104.939, 84.147, 117.762, 83.842, 119.681, 84.296, 104.039, "None", 82.398, 114.643, 113.064, 81.413, 120.387, 81.937, 102.323, "None", 87.049, 86.47, 86.65, 87.146, 86.914, 86.758, 87.722, 131.255, 104.583], "lap": [1.0, 2.0, 3.0, 4.0, 5.0, 6.0, 7.0, 8.0, 9.0, 10.0, 11.0, 12.0, 13.0, 14.0, 15.0, 16.0, 17.0, 18.0, 19.0, 20.0, 21.0, 22.0, 23.0, 24.0, 25.0, 26.0, 27.0], "compound": ["HARD", "HARD", "HARD", "HARD", "HARD", "HARD", "HARD", "HARD", "HARD", "SOFT", "SOFT", "SOFT", "SOFT", "SOFT", "SOFT", "SOFT", "SOFT", "HARD", "HARD", "HARD", "HARD", "HARD", "HARD", "HARD", "HARD", "HARD", "HARD"], "stint": [1, 1, 1, 1, 1, 1, 1, 1, 1, 2, 2, 2, 2, 2, 2, 2, 2, 3, 3, 3, 3, 3, 3, 3, 3, 3, 3], "s1": ["None", 30.776, 36.452, 29.949, 39.405, 29.858, 40.102, 29.908, 35.511, "None", 29.567, 37.912, 36.192, 29.132, 40.326, 29.012, 32.633, "None", 30.859, 30.644, 30.772, 30.953, 30.709, 30.704, 30.922, 32.678, 38.959], "s2": [36.477, 32.007, 42.143, 30.444, 49.389, 30.199, 44.555, 30.225, 38.35, 38.705, 29.682, 43.983, 42.937, 29.088, 43.27, 29.4, 39.25, 36.779, 31.586, 31.305, 31.259, 31.566, 31.374, 31.328, 31.39, 43.109, 37.093], "s3": [40.419, 24.361, 26.344, 23.754, 28.968, 23.785, 35.024, 24.163, 30.178, 28.822, 23.149, 32.748, 33.935, 23.193, 36.791, 23.525, 30.44, 25.724, 24.604, 24.521, 24.619, 24.627, 24.831, 24.726, 25.41, 55.468, 28.531], "life": [1, 2, 3, 4, 5, 6, 7, 8, 9, 1, 2, 3, 4, 5, 6, 7, 8, 10, 11, 12, 13, 14, 15, 16, 17, 18, 19], "pos": ["None", "None", "None", "None", "None", "None", "None", "None", "None", "None", "None", "None", "None", "None", "None", "None", "None", "None", "None", "None", "None", "None", "None", "None", "None", "None", "None"], "status": ["1", "12", "1", "1", "1", "1", "1", "1", "1", "1", "1", "1", "1", "1", "1", "1", "1", "1", "1", "1", "12", "1", "1", "1", "1", "1", "1"], "pb": [false, true, false, true, false, true, false, false, false, false, true, false, false, true, false, false, false, false, false, false, false, false, false, false, false, false, false]}