{"topSpeed": [{"Driver": "ALB", "TopSpeed": 310, "Compound": "SOFT", "Team": "Williams"}, {"Driver": "LAT", "TopSpeed": 308, "Compound": "SOFT", "Team": "Williams"}, {"Driver": "VET", "TopSpeed": 305, "Compound": "SOFT", "Team": "Aston Martin"}, {"Driver": "HAM", "TopSpeed": 305, "Compound": "SOFT", "Team": "Mercedes"}, {"Driver": "PER", "TopSpeed": 304, "Compound": "SOFT", "Team": "Red Bull Racing"}, {"Driver": "RUS", "TopSpeed": 304, "Compound": "SOFT", "Team": "Mercedes"}, {"Driver": "VER", "TopSpeed": 302, "Compound": "SOFT", "Team": "Red Bull Racing"}, {"Driver": "TSU", "TopSpeed": 302, "Compound": "SOFT", "Team": "AlphaTauri"}, {"Driver": "ZHO", "TopSpeed": 302, "Compound": "SOFT", "Team": "Alfa Romeo"}, {"Driver": "MAG", "TopSpeed": 302, "Compound": "SOFT", "Team": "Haas F1 Team"}, {"Driver": "GAS", "TopSpeed": 302, "Compound": "SOFT", "Team": "AlphaTauri"}, {"Driver": "MSC", "TopSpeed": 301, "Compound": "MEDIUM", "Team": "Haas F1 Team"}, {"Driver": "STR", "TopSpeed": 301, "Compound": "SOFT", "Team": "Aston Martin"}, {"Driver": "RIC", "TopSpeed": 300, "Compound": "SOFT", "Team": "McLaren"}, {"Driver": "LEC", "TopSpeed": 299, "Compound": "SOFT", "Team": "Ferrari"}, {"Driver": "BOT", "TopSpeed": 299, "Compound": "MEDIUM", "Team": "Alfa Romeo"}, {"Driver": "ALO", "TopSpeed": 298, "Compound": "MEDIUM", "Team": "Alpine"}, {"Driver": "SAI", "TopSpeed": 297, "Compound": "SOFT", "Team": "Ferrari"}, {"Driver": "NOR", "TopSpeed": 295, "Compound": "SOFT", "Team": "McLaren"}, {"Driver": "OCO", "TopSpeed": 295, "Compound": "MEDIUM", "Team": "Alpine"}]}