{"time": ["None", 111.558, 143.53, 109.941, 141.048, 110.318, 133.161, "None", 120.443, 113.797, 114.988, 114.848, 114.812, 114.744, 115.276, 115.702, 117.149, 118.485, 123.754, "None", "None", 141.332, "None"], "lap": [1.0, 2.0, 3.0, 4.0, 5.0, 6.0, 7.0, 8.0, 9.0, 10.0, 11.0, 12.0, 13.0, 14.0, 15.0, 16.0, 17.0, 18.0, 19.0, 20.0, 21.0, 22.0, 23.0], "compound": ["SOFT", "SOFT", "SOFT", "SOFT", "SOFT", "SOFT", "SOFT", "HARD", "HARD", "HARD", "HARD", "HARD", "HARD", "HARD", "HARD", "HARD", "HARD", "HARD", "HARD", "SOFT", "INTERMEDIATE", "INTERMEDIATE", "INTERMEDIATE"], "stint": [1, 1, 1, 1, 1, 1, 1, 2, 2, 2, 2, 2, 2, 2, 2, 2, 2, 2, 2, 3, 4, 4, 4], "s1": ["None", 31.634, 41.605, 31.477, 37.933, 31.656, 40.159, "None", 35.856, 32.669, 32.996, 32.843, 32.907, 32.86, 32.918, 32.933, 32.83, 33.271, 33.476, 50.566, "None", 34.945, 55.119], "s2": [60.027, 49.778, 69.074, 48.258, 66.275, 48.672, 55.305, 61.691, 53.655, 50.372, 50.983, 50.872, 50.749, 51.104, 51.022, 51.606, 52.348, 53.521, 54.656, 76.555, 57.66, 58.993, 58.643], "s3": [34.073, 30.146, 32.851, 30.206, 36.84, 29.99, 37.697, 37.627, 30.932, 30.756, 31.009, 31.133, 31.156, 30.78, 31.336, 31.163, 31.971, 31.693, 35.622, 39.614, 33.402, 47.394, "None"], "life": [1, 2, 3, 4, 5, 6, 7, 1, 2, 3, 4, 5, 6, 7, 8, 9, 10, 11, 12, 8, 5, 6, 7], "pos": ["None", "None", "None", "None", "None", "None", "None", "None", "None", "None", "None", "None", "None", "None", "None", "None", "None", "None", "None", "None", "None", "None", "None"], "status": ["1", "1", "1", "1", "1", "1", "1", "1", "1", "1", "1", "1", "12", "1", "1", "1", "1", "12", "1", "12", "1", "1", "1"], "pb": [false, true, false, true, false, false, false, false, false, false, false, false, false, false, false, false, false, false, false, false, false, false, false]}