{"time": [143.807, 129.155, 127.657, 126.887, 125.585, 126.2, "None"], "lap": [1.0, 2.0, 3.0, 4.0, 5.0, 6.0, 7.0], "compound": ["INTERMEDIATE", "INTERMEDIATE", "INTERMEDIATE", "INTERMEDIATE", "INTERMEDIATE", "INTERMEDIATE", "INTERMEDIATE"], "stint": [1, 1, 1, 1, 1, 1, 1], "s1": ["None", 33.306, 32.776, 32.268, 32.185, 32.2, 54.398], "s2": [54.762, 51.227, 50.914, 50.012, 49.597, 50.428, 70.305], "s3": [46.446, 44.622, 43.967, 44.607, 43.803, 43.572, 69.6], "life": [1, 2, 3, 4, 5, 6, 7], "pos": [17, 17, 17, 18, 18, 18, 19], "status": ["12", "1", "1", "1", "1", "1", "124"], "pb": [false, true, true, true, true, false, false]}