{"fastest": [{"Driver": "VER", "LapTime": 105.507, "Diff": 0.0, "Team": "Red Bull Racing"}, {"Driver": "LEC", "LapTime": 106.369, "Diff": 0.862, "Team": "Ferrari"}, {"Driver": "NOR", "LapTime": 106.589, "Diff": 1.082, "Team": "McLaren"}, {"Driver": "STR", "LapTime": 106.635, "Diff": 1.128, "Team": "Aston Martin"}, {"Driver": "SAI", "LapTime": 106.649, "Diff": 1.142, "Team": "Ferrari"}, {"Driver": "HAM", "LapTime": 106.893, "Diff": 1.386, "Team": "Mercedes"}, {"Driver": "ALO", "LapTime": 106.975, "Diff": 1.468, "Team": "Alpine"}, {"Driver": "RUS", "LapTime": 107.042, "Diff": 1.535, "Team": "Mercedes"}, {"Driver": "RIC", "LapTime": 107.255, "Diff": 1.748, "Team": "McLaren"}, {"Driver": "PER", "LapTime": 107.346, "Diff": 1.839, "Team": "Red Bull Racing"}, {"Driver": "ALB", "LapTime": 107.52, "Diff": 2.013, "Team": "Williams"}, {"Driver": "ZHO", "LapTime": 107.617, "Diff": 2.11, "Team": "Alfa Romeo"}, {"Driver": "TSU", "LapTime": 107.658, "Diff": 2.151, "Team": "AlphaTauri"}, {"Driver": "GAS", "LapTime": 107.782, "Diff": 2.275, "Team": "AlphaTauri"}, {"Driver": "VET", "LapTime": 107.867, "Diff": 2.36, "Team": "Aston Martin"}, {"Driver": "OCO", "LapTime": 107.944, "Diff": 2.437, "Team": "Alpine"}, {"Driver": "MAG", "LapTime": 108.208, "Diff": 2.701, "Team": "Haas F1 Team"}, {"Driver": "BOT", "LapTime": 108.419, "Diff": 2.912, "Team": "Alfa Romeo"}, {"Driver": "LAT", "LapTime": 108.612, "Diff": 3.105, "Team": "Williams"}, {"Driver": "MSC", "LapTime": 109.941, "Diff": 4.434, "Team": "Haas F1 Team"}]}