{"strategy": [{"Driver": "VER", "Stint": 1.0, "Compound": "INTERMEDIATE", "LapStart": 0.0, "FinishOrder": 1, "LapEnd": 19.0, "fill": "blue"}, {"Driver": "VER", "Stint": 2.0, "Compound": "MEDIUM", "LapStart": 19.0, "FinishOrder": 1, "LapEnd": 51.0, "fill": "yellow"}, {"Driver": "VER", "Stint": 3.0, "Compound": "SOFT", "LapStart": 51.0, "FinishOrder": 1, "LapEnd": 63.0, "fill": "red"}, {"Driver": "PER", "Stint": 3.0, "Compound": "SOFT", "LapStart": 50.0, "FinishOrder": 2, "LapEnd": 63.0, "fill": "red"}, {"Driver": "PER", "Stint": 2.0, "Compound": "MEDIUM", "LapStart": 18.0, "FinishOrder": 2, "LapEnd": 50.0, "fill": "yellow"}, {"Driver": "PER", "Stint": 1.0, "Compound": "INTERMEDIATE", "LapStart": 0.0, "FinishOrder": 2, "LapEnd": 18.0, "fill": "blue"}, {"Driver": "NOR", "Stint": 2.0, "Compound": "MEDIUM", "LapStart": 19.0, "FinishOrder": 3, "LapEnd": 63.0, "fill": "yellow"}, {"Driver": "NOR", "Stint": 1.0, "Compound": "INTERMEDIATE", "LapStart": 0.0, "FinishOrder": 3, "LapEnd": 19.0, "fill": "blue"}, {"Driver": "RUS", "Stint": 1.0, "Compound": "INTERMEDIATE", "LapStart": 0.0, "FinishOrder": 4, "LapEnd": 18.0, "fill": "blue"}, {"Driver": "RUS", "Stint": 2.0, "Compound": "MEDIUM", "LapStart": 18.0, "FinishOrder": 4, "LapEnd": 63.0, "fill": "yellow"}, {"Driver": "BOT", "Stint": 1.0, "Compound": "INTERMEDIATE", "LapStart": 0.0, "FinishOrder": 5, "LapEnd": 18.0, "fill": "blue"}, {"Driver": "BOT", "Stint": 2.0, "Compound": "MEDIUM", "LapStart": 18.0, "FinishOrder": 5, "LapEnd": 63.0, "fill": "yellow"}, {"Driver": "LEC", "Stint": 3.0, "Compound": "SOFT", "LapStart": 49.0, "FinishOrder": 6, "LapEnd": 53.0, "fill": "red"}, {"Driver": "LEC", "Stint": 4.0, "Compound": "SOFT", "LapStart": 53.0, "FinishOrder": 6, "LapEnd": 63.0, "fill": "red"}, {"Driver": "LEC", "Stint": 1.0, "Compound": "INTERMEDIATE", "LapStart": 0.0, "FinishOrder": 6, "LapEnd": 19.0, "fill": "blue"}, {"Driver": "LEC", "Stint": 2.0, "Compound": "MEDIUM", "LapStart": 19.0, "FinishOrder": 6, "LapEnd": 49.0, "fill": "yellow"}, {"Driver": "TSU", "Stint": 2.0, "Compound": "MEDIUM", "LapStart": 18.0, "FinishOrder": 7, "LapEnd": 63.0, "fill": "yellow"}, {"Driver": "TSU", "Stint": 1.0, "Compound": "INTERMEDIATE", "LapStart": 0.0, "FinishOrder": 7, "LapEnd": 18.0, "fill": "blue"}, {"Driver": "VET", "Stint": 1.0, "Compound": "INTERMEDIATE", "LapStart": 0.0, "FinishOrder": 8, "LapEnd": 17.0, "fill": "blue"}, {"Driver": "VET", "Stint": 2.0, "Compound": "MEDIUM", "LapStart": 17.0, "FinishOrder": 8, "LapEnd": 63.0, "fill": "yellow"}, {"Driver": "MAG", "Stint": 1.0, "Compound": "INTERMEDIATE", "LapStart": 0.0, "FinishOrder": 9, "LapEnd": 18.0, "fill": "blue"}, {"Driver": "MAG", "Stint": 2.0, "Compound": "MEDIUM", "LapStart": 18.0, "FinishOrder": 9, "LapEnd": 63.0, "fill": "yellow"}, {"Driver": "STR", "Stint": 2.0, "Compound": "MEDIUM", "LapStart": 18.0, "FinishOrder": 10, "LapEnd": 62.0, "fill": "yellow"}, {"Driver": "STR", "Stint": 1.0, "Compound": "INTERMEDIATE", "LapStart": 0.0, "FinishOrder": 10, "LapEnd": 18.0, "fill": "blue"}, {"Driver": "ALB", "Stint": 2.0, "Compound": "MEDIUM", "LapStart": 17.0, "FinishOrder": 11, "LapEnd": 62.0, "fill": "yellow"}, {"Driver": "ALB", "Stint": 1.0, "Compound": "INTERMEDIATE", "LapStart": 0.0, "FinishOrder": 11, "LapEnd": 17.0, "fill": "blue"}, {"Driver": "GAS", "Stint": 2.0, "Compound": "MEDIUM", "LapStart": 17.0, "FinishOrder": 12, "LapEnd": 62.0, "fill": "yellow"}, {"Driver": "GAS", "Stint": 1.0, "Compound": "INTERMEDIATE", "LapStart": 0.0, "FinishOrder": 12, "LapEnd": 17.0, "fill": "blue"}, {"Driver": "HAM", "Stint": 2.0, "Compound": "MEDIUM", "LapStart": 18.0, "FinishOrder": 13, "LapEnd": 62.0, "fill": "yellow"}, {"Driver": "HAM", "Stint": 1.0, "Compound": "INTERMEDIATE", "LapStart": 0.0, "FinishOrder": 13, "LapEnd": 18.0, "fill": "blue"}, {"Driver": "OCO", "Stint": 1.0, "Compound": "INTERMEDIATE", "LapStart": 0.0, "FinishOrder": 14, "LapEnd": 18.0, "fill": "blue"}, {"Driver": "OCO", "Stint": 2.0, "Compound": "MEDIUM", "LapStart": 18.0, "FinishOrder": 14, "LapEnd": 62.0, "fill": "yellow"}, {"Driver": "ZHO", "Stint": 1.0, "Compound": "INTERMEDIATE", "LapStart": 0.0, "FinishOrder": 15, "LapEnd": 18.0, "fill": "blue"}, {"Driver": "ZHO", "Stint": 2.0, "Compound": "MEDIUM", "LapStart": 18.0, "FinishOrder": 15, "LapEnd": 62.0, "fill": "yellow"}, {"Driver": "LAT", "Stint": 2.0, "Compound": "MEDIUM", "LapStart": 18.0, "FinishOrder": 16, "LapEnd": 62.0, "fill": "yellow"}, {"Driver": "LAT", "Stint": 1.0, "Compound": "INTERMEDIATE", "LapStart": 0.0, "FinishOrder": 16, "LapEnd": 18.0, "fill": "blue"}, {"Driver": "MSC", "Stint": 3.0, "Compound": "SOFT", "LapStart": 52.0, "FinishOrder": 17, "LapEnd": 62.0, "fill": "red"}, {"Driver": "MSC", "Stint": 2.0, "Compound": "MEDIUM", "LapStart": 18.0, "FinishOrder": 17, "LapEnd": 52.0, "fill": "yellow"}, {"Driver": "MSC", "Stint": 1.0, "Compound": "INTERMEDIATE", "LapStart": 0.0, "FinishOrder": 17, "LapEnd": 18.0, "fill": "blue"}, {"Driver": "RIC", "Stint": 3.0, "Compound": "MEDIUM", "LapStart": 16.0, "FinishOrder": 18, "LapEnd": 30.0, "fill": "yellow"}, {"Driver": "RIC", "Stint": 2.0, "Compound": "INTERMEDIATE", "LapStart": 2.0, "FinishOrder": 18, "LapEnd": 16.0, "fill": "blue"}, {"Driver": "RIC", "Stint": 1.0, "Compound": "INTERMEDIATE", "LapStart": 0.0, "FinishOrder": 18, "LapEnd": 2.0, "fill": "blue"}, {"Driver": "RIC", "Stint": 4.0, "Compound": "HARD", "LapStart": 30.0, "FinishOrder": 18, "LapEnd": 62.0, "fill": "white"}, {"Driver": "ALO", "Stint": 1.0, "Compound": "INTERMEDIATE", "LapStart": 0.0, "FinishOrder": 19, "LapEnd": 6.0, "fill": "blue"}, {"Driver": "SAI", "Stint": 1.0, "Compound": "INTERMEDIATE", "LapStart": 0.0, "FinishOrder": 20, "LapEnd": 1.0, "fill": "blue"}]}