{"time": ["None", 98.128, 137.322, "None", "None", 103.261, 96.367, 120.397, "None", 102.48, "None", 130.516, 94.943, 110.513, "None", 132.316, 145.073], "lap": [1.0, 2.0, 3.0, 4.0, 5.0, 6.0, 7.0, 8.0, 9.0, 10.0, 11.0, 12.0, 13.0, 14.0, 15.0, 16.0, 17.0], "compound": ["MEDIUM", "MEDIUM", "MEDIUM", "MEDIUM", "MEDIUM", "MEDIUM", "MEDIUM", "MEDIUM", "MEDIUM", "MEDIUM", "SOFT", "SOFT", "SOFT", "SOFT", "SOFT", "SOFT", "SOFT"], "stint": [1, 1, 1, 1, 2, 2, 2, 2, 3, 3, 4, 4, 4, 4, 5, 5, 5], "s1": ["None", 31.951, 46.82, 35.65, "None", 31.666, 31.091, 36.034, "None", 31.974, "None", 37.936, 30.512, 34.386, "None", 36.122, 69.102], "s2": [58.439, 42.129, 58.827, 57.648, 48.868, 43.846, 41.28, 53.593, 49.174, 43.773, 49.566, 55.314, 40.613, 48.468, 46.198, 50.82, 47.23], "s3": [35.276, 24.048, 31.675, "None", 33.174, 27.749, 23.996, 30.77, 26.922, 26.733, 29.784, 37.266, 23.818, 27.659, 25.829, 45.374, 28.741], "life": [1, 2, 3, 4, 5, 6, 7, 8, 9, 10, 1, 2, 3, 4, 5, 6, 7], "pos": ["None", "None", "None", "None", "None", "None", "None", "None", "None", "None", "None", "None", "None", "None", "None", "None", "None"], "status": ["1", "1", "12", "251", "1", "1", "1", "1", "12", "1", "12", "1", "1", "1", "1", "1", "1"], "pb": [false, true, false, false, false, false, true, false, false, false, false, false, true, false, false, false, false]}