{"time": ["None", 88.329, 87.017, 86.306, 86.255, 85.689, 85.503, 85.555, 85.8, 86.349, 84.775, 110.216, "None", 82.99, 133.736, 140.085, 82.689, 115.557, "None", 86.935, 88.417, 85.866, 85.8, 85.854, 85.939, 110.237, "None"], "lap": [1.0, 2.0, 3.0, 4.0, 5.0, 6.0, 7.0, 8.0, 9.0, 10.0, 11.0, 12.0, 13.0, 14.0, 15.0, 16.0, 17.0, 18.0, 19.0, 20.0, 21.0, 22.0, 23.0, 24.0, 25.0, 26.0, 27.0], "compound": ["HARD", "HARD", "HARD", "HARD", "HARD", "HARD", "HARD", "HARD", "HARD", "HARD", "HARD", "HARD", "SOFT", "SOFT", "SOFT", "SOFT", "SOFT", "SOFT", "SOFT", "SOFT", "SOFT", "SOFT", "SOFT", "SOFT", "SOFT", "SOFT", "SOFT"], "stint": [1, 1, 1, 1, 1, 1, 1, 1, 1, 1, 1, 1, 2, 2, 2, 3, 3, 3, 4, 4, 4, 4, 4, 4, 4, 4, 4], "s1": ["None", 29.073, 28.638, 28.285, 28.587, 28.253, 28.227, 28.15, 28.182, 28.278, 27.803, 37.697, "None", 27.619, 40.77, 62.739, 27.493, 37.684, "None", 28.488, 28.484, 28.294, 28.255, 28.213, 27.983, 34.491, 75.179], "s2": [31.203, 30.148, 29.642, 29.261, 29.072, 28.998, 28.888, 28.979, 29.144, 28.964, 28.822, 36.147, 32.045, 27.884, 45.656, 41.922, 27.809, 36.442, 38.758, 29.698, 31.293, 29.098, 29.212, 29.152, 29.54, 36.114, 38.757], "s3": [31.318, 29.108, 28.737, 28.76, 28.596, 28.438, 28.388, 28.426, 28.474, 29.107, 28.15, 36.372, 30.752, 27.487, 47.31, 35.424, 27.387, 41.431, 29.554, 28.749, 28.64, 28.474, 28.333, 28.489, 28.416, 39.632, 40.35], "life": [1, 2, 3, 4, 5, 6, 7, 8, 9, 10, 11, 12, 1, 2, 3, 4, 5, 6, 7, 8, 9, 10, 11, 12, 13, 14, 15], "pos": ["None", "None", "None", "None", "None", "None", "None", "None", "None", "None", "None", "None", "None", "None", "None", "None", "None", "None", "None", "None", "None", "None", "None", "None", "None", "None", "None"], "status": ["1", "1", "1", "1", "1", "1", "1", "1", "1", "1", "1", "1", "1", "1", "1", "1", "1", "1", "1", "1", "1", "1", "1", "1", "1", "1", "1"], "pb": [false, true, true, true, true, true, true, false, false, false, true, false, false, true, false, false, true, false, false, false, false, false, false, false, false, false, false]}